opentnsim/__init__.py
opentnsim/cli.py
opentnsim/constants.py
opentnsim/fis.py
opentnsim/model.py
opentnsim/output.py
opentnsim/plot.py
opentnsim/strategy.py
opentnsim/utils.py
opentnsim/core/__init__.py
opentnsim/core/container.py
opentnsim/core/logutils.py
opentnsim/core/misc.py
opentnsim/core/movable.py
opentnsim/core/plotutils.py
opentnsim/core/resource.py
opentnsim/core/vessel_properties.py
opentnsim/data/Correctionfactors.csv
opentnsim/data/KarpovSmoothCurves.csv
opentnsim/energy/__init__.py
opentnsim/energy/algorithms.py
opentnsim/energy/calculations.py
opentnsim/energy/logutils.py
opentnsim/energy/mixins.py
opentnsim/graph/__init__.py
opentnsim/graph/mixins.py
opentnsim/graph/utils.py
opentnsim/lock/__init__.py
opentnsim/lock/calculations.py
opentnsim/lock/lock.py
opentnsim/lock/lock_chamber.py
opentnsim/lock/logutils.py
opentnsim/lock/utils.py
opentnsim/vessel_traffic_service/__init__.py
opentnsim/vessel_traffic_service/hydrodanamic_data_manager.py
opentnsim/vessel_traffic_service/vessel_traffic_service.py
opentnsim-2.2.2.dist-info/METADATA
opentnsim-2.2.2.dist-info/WHEEL
opentnsim-2.2.2.dist-info/entry_points.txt
opentnsim-2.2.2.dist-info/licenses/AUTHORS.rst
opentnsim-2.2.2.dist-info/licenses/LICENSE.txt
opentnsim-2.2.2.dist-info/RECORD
