Metadata-Version: 2.4
Name: opentnsim
Version: 2.2.2
Summary: The OpenTNSim package aims to facilitate the analysis of network performance for different network configurations, fleet compositions and traffic rules.
Project-URL: Homepage, https://github.com/TUDelft-CITG/OpenTNSim
Author-email: Mark van Koningsveld <m.vankoningsveld@tudelft.nl>
License-Expression: MIT
License-File: AUTHORS.rst
License-File: LICENSE.txt
Keywords: OpenCLSim,OpenTNSim,simulation,transport
Classifier: Development Status :: 2 - Pre-Alpha
Classifier: Intended Audience :: Developers
Classifier: Natural Language :: English
Classifier: Programming Language :: Python :: 3
Requires-Python: <4,>=3.12
Requires-Dist: click<9,>=8.1.8
Requires-Dist: deprecated>=1.2.18
Requires-Dist: geopandas>=1.0.1
Requires-Dist: matplotlib>=3.10.1
Requires-Dist: networkx>=3.4.2
Requires-Dist: openclsim>=1.6.2
Requires-Dist: pandas>=2.2.3
Requires-Dist: pytz>=2025.2
Requires-Dist: pyyaml>=6.0.3
Requires-Dist: requests-cache>=1.2.1
Requires-Dist: scipy>=1.15.2
Requires-Dist: shapely>=2.1.0
Requires-Dist: simplekml>=1.3.6
Requires-Dist: simpy>=4.1.1
Requires-Dist: sphinx>=7.4.7
Requires-Dist: tqdm>=4.67.1
Requires-Dist: xarray>=2025.3.1
Provides-Extra: testing
Requires-Dist: anywidget; extra == 'testing'
Requires-Dist: colorcet>=3.1.0; extra == 'testing'
Requires-Dist: cython>=3.1.0; extra == 'testing'
Requires-Dist: fiona>=1.10.1; extra == 'testing'
Requires-Dist: folium>=0.19.5; extra == 'testing'
Requires-Dist: ipykernel>=6.29.5; extra == 'testing'
Requires-Dist: ipyleaflet>=0.19.2; extra == 'testing'
Requires-Dist: ipywidgets>=8.1.7; extra == 'testing'
Requires-Dist: jsonschema>=4.23.0; extra == 'testing'
Requires-Dist: jupyter-book<2,>=1.0.4.post1; extra == 'testing'
Requires-Dist: jupyter>=1.1.1; extra == 'testing'
Requires-Dist: jupyterlab-widgets>=3.0.15; extra == 'testing'
Requires-Dist: lonboard>=0.11.1; extra == 'testing'
Requires-Dist: mapclassify>=2.10.0; extra == 'testing'
Requires-Dist: momepy>=0.10.0; extra == 'testing'
Requires-Dist: movingpandas[smoothing,viz]>=0.22.4; extra == 'testing'
Requires-Dist: nbconvert>=7.16.6; extra == 'testing'
Requires-Dist: nbmake>=1.5.5; extra == 'testing'
Requires-Dist: notebook>=7.4.2; extra == 'testing'
Requires-Dist: openpyxl>=3.1.5; extra == 'testing'
Requires-Dist: pyarrow; extra == 'testing'
Requires-Dist: pytest-cov>=6.1.1; extra == 'testing'
Requires-Dist: pytest-datadir>=1.6.1; extra == 'testing'
Requires-Dist: pytest-timeout>=2.3.1; extra == 'testing'
Requires-Dist: pytest>=8.3.5; extra == 'testing'
Requires-Dist: pyyaml>=6.0.2; extra == 'testing'
Requires-Dist: sphinx-rtd-theme>=3.0.2; extra == 'testing'
